finesse_ligo/ASC_controllers.py
finesse_ligo/__init__.py
finesse_ligo/_version.py
finesse_ligo/actions.py
finesse_ligo/asc.py
finesse_ligo/lho.py
finesse_ligo/llo.py
finesse_ligo/maps.py
finesse_ligo/suspension.py
finesse_ligo/thermal.py
finesse_ligo/tools.py
finesse_ligo/data/__init__.py
finesse_ligo/data/ASC/H1ASC.txt
finesse_ligo/data/maps/O5_nominal_surface_profiles.npz
finesse_ligo/data/maps/__init__.py
finesse_ligo/data/suspensions/__init__.py
finesse_ligo/data/suspensions/ligo_triple_suspension_ss.pbz2
finesse_ligo/data/suspensions/quad_damped_zpk.h5
finesse_ligo/data/thermal/T2100329-v1-ringheater_FEA.npz
finesse_ligo/data/thermal/__init__.py
finesse_ligo/katscript/__init__.py
finesse_ligo/katscript/aligo.kat
finesse_ligo/katscript/aligo_reversed_itm.kat
finesse_ligo/katscript/arm.kat
finesse_ligo-1.0.15.dist-info/METADATA
finesse_ligo-1.0.15.dist-info/WHEEL
finesse_ligo-1.0.15.dist-info/top_level.txt
finesse_ligo-1.0.15.dist-info/RECORD
