Metadata-Version: 2.1
Name: finesse-ligo
Version: 1.0.15
Summary: Tools for modelling LIGO in Finesse 3.0
Home-page: https://gitlab.com/ifosim/finesse/finesse-ligo
Author: Daniel Brown
Author-email: daniel.brown@LIGO.org
Project-URL: Bug Tracker, https://gitlab.com/ifosim/finesse/finesse-ligo/issues
Classifier: Programming Language :: Python :: 3
Classifier: Operating System :: OS Independent
Classifier: Topic :: Scientific/Engineering :: Physics
Classifier: Intended Audience :: Science/Research
Classifier: Natural Language :: English
Classifier: License :: OSI Approved :: GNU General Public License v3 or later (GPLv3+)
Requires-Python: >=3.8
Requires-Dist: finesse
Requires-Dist: numpy
Requires-Dist: scipy
Requires-Dist: matplotlib
Requires-Dist: control
Requires-Dist: tqdm
Requires-Dist: more-itertools
